tusk/__init__.py
tusk/cli.py
tusk/admin/__init__.py
tusk/admin/backup.py
tusk/admin/extensions.py
tusk/admin/maintenance.py
tusk/admin/monitoring.py
tusk/admin/pitr.py
tusk/admin/processes.py
tusk/admin/roles.py
tusk/admin/settings.py
tusk/admin/stats.py
tusk/cluster/__init__.py
tusk/cluster/models.py
tusk/cluster/scheduler.py
tusk/cluster/worker.py
tusk/core/__init__.py
tusk/core/auth.py
tusk/core/config.py
tusk/core/connection.py
tusk/core/deps.py
tusk/core/files.py
tusk/core/geo.py
tusk/core/history.py
tusk/core/logging.py
tusk/core/result.py
tusk/core/scheduled_tasks.py
tusk/core/scheduler.py
tusk/core/workspace.py
tusk/engines/__init__.py
tusk/engines/duckdb_engine.py
tusk/engines/polars_engine.py
tusk/engines/postgres.py
tusk/engines/sqlite.py
tusk/studio/__init__.py
tusk/studio/app.py
tusk/studio/routes/__init__.py
tusk/studio/routes/admin.py
tusk/studio/routes/api.py
tusk/studio/routes/auth.py
tusk/studio/routes/cluster.py
tusk/studio/routes/data.py
tusk/studio/routes/files.py
tusk/studio/routes/pages.py
tusk/studio/routes/scheduler.py
tusk/studio/routes/settings.py
tusk/studio/static/.gitkeep
tusk/studio/static/admin.js
tusk/studio/static/cluster.js
tusk/studio/static/data.js
tusk/studio/static/profile.js
tusk/studio/static/studio.js
tusk/studio/static/styles.css
tusk/studio/static/users.js
tusk/studio/templates/admin.html
tusk/studio/templates/base.html
tusk/studio/templates/cluster.html
tusk/studio/templates/data.html
tusk/studio/templates/index.html
tusk/studio/templates/login.html
tusk/studio/templates/profile.html
tusk/studio/templates/users.html
tuskdata-0.1.2.dist-info/METADATA
tuskdata-0.1.2.dist-info/WHEEL
tuskdata-0.1.2.dist-info/entry_points.txt
tuskdata-0.1.2.dist-info/RECORD
