Metadata-Version: 2.4
Name: tuskdata
Version: 0.1.2
Summary: Modern data platform - PostgreSQL admin + Analytics engine
Project-URL: Homepage, https://github.com/tuskdata/tuskdata
Project-URL: Repository, https://github.com/tuskdata/tuskdata
Project-URL: Issues, https://github.com/tuskdata/tuskdata/issues
Author: TuskData Team
License-Expression: MIT
Keywords: admin,analytics,database,duckdb,etl,polars,postgresql,sql
Classifier: Development Status :: 3 - Alpha
Classifier: Environment :: Web Environment
Classifier: Framework :: AsyncIO
Classifier: Intended Audience :: Developers
Classifier: Intended Audience :: System Administrators
Classifier: License :: OSI Approved :: MIT License
Classifier: Operating System :: OS Independent
Classifier: Programming Language :: Python :: 3
Classifier: Programming Language :: Python :: 3.11
Classifier: Programming Language :: Python :: 3.12
Classifier: Programming Language :: Python :: 3.13
Classifier: Topic :: Database
Classifier: Topic :: Database :: Database Engines/Servers
Requires-Python: >=3.11
Requires-Dist: httpx>=0.27
Requires-Dist: msgspec>=0.18
Requires-Dist: structlog>=24.0
Requires-Dist: tomli-w>=1.0
Provides-Extra: admin
Requires-Dist: apscheduler>=3.11.2; extra == 'admin'
Requires-Dist: psutil>=5.9; extra == 'admin'
Provides-Extra: all
Requires-Dist: apscheduler>=3.10; extra == 'all'
Requires-Dist: apscheduler>=3.11.2; extra == 'all'
Requires-Dist: datafusion>=51.0; extra == 'all'
Requires-Dist: duckdb>=1.0; extra == 'all'
Requires-Dist: granian>=2.0; extra == 'all'
Requires-Dist: jinja2>=3.0; extra == 'all'
Requires-Dist: litestar>=2.0; extra == 'all'
Requires-Dist: minijinja>=2.0; extra == 'all'
Requires-Dist: polars>=1.0; extra == 'all'
Requires-Dist: psutil>=5.9; extra == 'all'
Requires-Dist: psycopg[binary]>=3.0; extra == 'all'
Requires-Dist: pyarrow>=17.0; extra == 'all'
Provides-Extra: cluster
Requires-Dist: datafusion>=51.0; extra == 'cluster'
Requires-Dist: pyarrow>=17.0; extra == 'cluster'
Provides-Extra: postgres
Requires-Dist: psycopg[binary]>=3.0; extra == 'postgres'
Provides-Extra: studio
Requires-Dist: apscheduler>=3.10; extra == 'studio'
Requires-Dist: duckdb>=1.0; extra == 'studio'
Requires-Dist: granian>=2.0; extra == 'studio'
Requires-Dist: jinja2>=3.0; extra == 'studio'
Requires-Dist: litestar>=2.0; extra == 'studio'
Requires-Dist: minijinja>=2.0; extra == 'studio'
Requires-Dist: polars>=1.0; extra == 'studio'
Requires-Dist: psycopg[binary]>=3.0; extra == 'studio'
Requires-Dist: pyarrow>=17.0; extra == 'studio'
